<?xml version='1.0' encoding='UTF-8' standalone='no'?>

    <recordset>
        <record id="id0">
            <aankomst>
                <datum>
                    <d>13</d>
                    <m>12</m>
                    <j>04</j>
                </datum>
                <tijd>
                    <van>0.00</van>
                    <tot>0.10</tot>
                </tijd>
                <soort_vervoer>vrachtauto</soort_vervoer>
                <bedrijf>DijckLogisticsBV</bedrijf>
                <positie>
                    <x>1</x>
                    <y>0</y>
                    <z>0</z>
                </positie>
            </aankomst>
            <eigenaar>
                <naam>FlowersNL</naam>
                <containernr>19965</containernr>
            </eigenaar>
            <vertrek>
                <datum>
                    <d>22</d>
                    <m>12</m>
                    <j>04</j>
                </datum>
                <tijd>
                    <van>0.00</van>
                    <tot>12.00</tot>
                </tijd>
                <soort_vervoer>zeeschip</soort_vervoer>
                <bedrijf>ChinaShippingAgency</bedrijf>
            </vertrek>
            <afmetingen>
                <l>40'</l>
                <b>8'</b>
                <h>8'6''</h>
            </afmetingen>
            <gewicht>
                <leeg>3</leeg>
                <inhoud>78</inhoud>
            </gewicht>
            <inhoud>
                <naam>nitrotolueen</naam>
                <soort>gas</soort>
                <gevaar>brandbaar</gevaar>
            </inhoud>
            <ISO>1496-1</ISO>
        </record>
        <record id="id1">
            <aankomst>
                <datum>
                    <d>2</d>
                    <m>12</m>
                    <j>04</j>
                </datum>
                <tijd>
                    <van>0.00</van>
                    <tot>0.10</tot>
                </tijd>
                <soort_vervoer>vrachtauto</soort_vervoer>
                <bedrijf>LindenOITTransportBV</bedrijf>
                <positie>
                    <x>1</x>
                    <y>0</y>
                    <z>0</z>
                </positie>
            </aankomst>
            <eigenaar>
                <naam>FederalExpress</naam>
                <containernr>89603</containernr>
            </eigenaar>
            <vertrek>
                <datum>
                    <d>4</d>
                    <m>12</m>
                    <j>04</j>
                </datum>
                <tijd>
                    <van>0.00</van>
                    <tot>12.00</tot>
                </tijd>
                <soort_vervoer>zeeschip</soort_vervoer>
                <bedrijf>BeaverShipsAgents</bedrijf>
            </vertrek>
            <afmetingen>
                <l>20'</l>
                <b>8'</b>
                <h>8'6''</h>
            </afmetingen>
            <gewicht>
                <leeg>2</leeg>
                <inhoud>25</inhoud>
            </gewicht>
            <inhoud>
                <naam>onderdelen</naam>
                <soort>los</soort>
                <gevaar>geen</gevaar>
            </inhoud>
            <ISO>1496-1</ISO>
        </record>
        <record id="id2">
            <aankomst>
                <datum>
                    <d>14</d>
                    <m>12</m>
                    <j>04</j>
                </datum>
                <tijd>
                    <van>0.00</van>
                    <tot>0.10</tot>
                </tijd>
                <soort_vervoer>vrachtauto</soort_vervoer>
                <bedrijf>DHL</bedrijf>
                <positie>
                    <x>1</x>
                    <y>0</y>
                    <z>0</z>
                </positie>
            </aankomst>
            <eigenaar>
                <naam>IntTrans</naam>
                <containernr>4219</containernr>
            </eigenaar>
            <vertrek>
                <datum>
                    <d>22</d>
                    <m>12</m>
                    <j>04</j>
                </datum>
                <tijd>
                    <van>0.00</van>
                    <tot>12.00</tot>
                </tijd>
                <soort_vervoer>zeeschip</soort_vervoer>
                <bedrijf>DutchGeneralCargo</bedrijf>
            </vertrek>
            <afmetingen>
                <l>40'</l>
                <b>8'</b>
                <h>8'6''</h>
            </afmetingen>
            <gewicht>
                <leeg>3</leeg>
                <inhoud>68</inhoud>
            </gewicht>
            <inhoud>
                <naam>pianos</naam>
                <soort>los</soort>
                <gevaar>brandbaar</gevaar>
            </inhoud>
            <ISO>1496-1</ISO>
        </record>
        <record id="id3">
            <aankomst>
                <datum>
                    <d>12</d>
                    <m>12</m>
                    <j>04</j>
                </datum>
                <tijd>
                    <van>0.00</van>
                    <tot>0.10</tot>
                </tijd>
                <soort_vervoer>vrachtauto</soort_vervoer>
                <bedrijf>DijckLogisticsBV</bedrijf>
                <positie>
                    <x>1</x>
                    <y>0</y>
                    <z>0</z>
                </positie>
            </aankomst>
            <eigenaar>
                <naam>KraftFoods</naam>
                <containernr>1428</containernr>
            </eigenaar>
            <vertrek>
                <datum>
                    <d>25</d>
                    <m>12</m>
                    <j>04</j>
                </datum>
                <tijd>
                    <van>0.00</van>
                    <tot>12.00</tot>
                </tijd>
                <soort_vervoer>zeeschip</soort_vervoer>
                <bedrijf>OceanTransIntBV</bedrijf>
            </vertrek>
            <afmetingen>
                <l>25'</l>
                <b>8'</b>
                <h>8'6''</h>
            </afmetingen>
            <gewicht>
                <leeg>2</leeg>
                <inhoud>45</inhoud>
            </gewicht>
            <inhoud>
                <naam>bier</naam>
                <soort>los</soort>
                <gevaar>vloeibaar</gevaar>
            </inhoud>
            <ISO>1496-1</ISO>
        </record>
        <record id="id4">
            <aankomst>
                <datum>
                    <d>17</d>
                    <m>12</m>
                    <j>04</j>
                </datum>
                <tijd>
                    <van>0.00</van>
                    <tot>0.10</tot>
                </tijd>
                <soort_vervoer>vrachtauto</soort_vervoer>
                <bedrijf>DHL</bedrijf>
                <positie>
                    <x>1</x>
                    <y>0</y>
                    <z>0</z>
                </positie>
            </aankomst>
            <eigenaar>
                <naam>UPS</naam>
                <containernr>67146</containernr>
            </eigenaar>
            <vertrek>
                <datum>
                    <d>19</d>
                    <m>12</m>
                    <j>04</j>
                </datum>
                <tijd>
                    <van>0.00</van>
                    <tot>3.00</tot>
                </tijd>
                <soort_vervoer>binnenschip</soort_vervoer>
                <bedrijf>FeederlinkBV</bedrijf>
            </vertrek>
            <afmetingen>
                <l>24'</l>
                <b>8'</b>
                <h>8'6''</h>
            </afmetingen>
            <gewicht>
                <leeg>2</leeg>
                <inhoud>44</inhoud>
            </gewicht>
            <inhoud>
                <naam>witgoed</naam>
                <soort>los</soort>
                <gevaar>geen</gevaar>
            </inhoud>
            <ISO>1496-1</ISO>
        </record>
        <record id="id5">
            <aankomst>
                <datum>
                    <d>23</d>
                    <m>12</m>
                    <j>04</j>
                </datum>
                <tijd>
                    <van>0.00</van>
                    <tot>0.10</tot>
                </tijd>
                <soort_vervoer>vrachtauto</soort_vervoer>
                <bedrijf>UPC</bedrijf>
                <positie>
                    <x>1</x>
                    <y>0</y>
                    <z>0</z>
                </positie>
            </aankomst>
            <eigenaar>
                <naam>UPS</naam>
                <containernr>46753</containernr>
            </eigenaar>
            <vertrek>
                <datum>
                    <d>25</d>
                    <m>12</m>
                    <j>04</j>
                </datum>
                <tijd>
                    <van>0.00</van>
                    <tot>3.00</tot>
                </tijd>
                <soort_vervoer>binnenschip</soort_vervoer>
                <bedrijf>GevelcoLogistic</bedrijf>
            </vertrek>
            <afmetingen>
                <l>20'</l>
                <b>8'</b>
                <h>8'6''</h>
            </afmetingen>
            <gewicht>
                <leeg>2</leeg>
                <inhoud>35</inhoud>
            </gewicht>
            <inhoud>
                <naam>karton</naam>
                <soort>los</soort>
                <gevaar>brandbaar</gevaar>
            </inhoud>
            <ISO>1496-1</ISO>
        </record>
        <record id="id6">
            <aankomst>
                <datum>
                    <d>13</d>
                    <m>12</m>
                    <j>04</j>
                </datum>
                <tijd>
                    <van>0.00</van>
                    <tot>0.10</tot>
                </tijd>
                <soort_vervoer>vrachtauto</soort_vervoer>
                <bedrijf>wegNL</bedrijf>
                <positie>
                    <x>1</x>
                    <y>0</y>
                    <z>0</z>
                </positie>
            </aankomst>
            <eigenaar>
                <naam>CocaCola</naam>
                <containernr>91492</containernr>
            </eigenaar>
            <vertrek>
                <datum>
                    <d>14</d>
                    <m>12</m>
                    <j>04</j>
                </datum>
                <tijd>
                    <van>0.00</van>
                    <tot>3.00</tot>
                </tijd>
                <soort_vervoer>binnenschip</soort_vervoer>
                <bedrijf>HerningRotterdam</bedrijf>
            </vertrek>
            <afmetingen>
                <l>25'</l>
                <b>8'</b>
                <h>8'6''</h>
            </afmetingen>
            <gewicht>
                <leeg>2</leeg>
                <inhoud>32</inhoud>
            </gewicht>
            <inhoud>
                <naam>witgoed</naam>
                <soort>los</soort>
                <gevaar>geen</gevaar>
            </inhoud>
            <ISO>1496-1</ISO>
        </record>
        <record id="id7">
            <aankomst>
                <datum>
                    <d>23</d>
                    <m>12</m>
                    <j>04</j>
                </datum>
                <tijd>
                    <van>0.00</van>
                    <tot>0.10</tot>
                </tijd>
                <soort_vervoer>vrachtauto</soort_vervoer>
                <bedrijf>WelpaTransBV</bedrijf>
                <positie>
                    <x>1</x>
                    <y>0</y>
                    <z>0</z>
                </positie>
            </aankomst>
            <eigenaar>
                <naam>Hanjin</naam>
                <containernr>52666</containernr>
            </eigenaar>
            <vertrek>
                <datum>
                    <d>31</d>
                    <m>12</m>
                    <j>04</j>
                </datum>
                <tijd>
                    <van>0.00</van>
                    <tot>3.00</tot>
                </tijd>
                <soort_vervoer>binnenschip</soort_vervoer>
                <bedrijf>CapelleChartering</bedrijf>
            </vertrek>
            <afmetingen>
                <l>20'</l>
                <b>8'</b>
                <h>8'6''</h>
            </afmetingen>
            <gewicht>
                <leeg>2</leeg>
                <inhoud>31</inhoud>
            </gewicht>
            <inhoud>
                <naam>papier</naam>
                <soort>vast</soort>
                <gevaar>brandbaar</gevaar>
            </inhoud>
            <ISO>1496-1</ISO>
        </record>
        <record id="id8">
            <aankomst>
                <datum>
                    <d>27</d>
                    <m>12</m>
                    <j>04</j>
                </datum>
                <tijd>
                    <van>0.00</van>
                    <tot>0.10</tot>
                </tijd>
                <soort_vervoer>vrachtauto</soort_vervoer>
                <bedrijf>KaspersTransportBV</bedrijf>
                <positie>
                    <x>1</x>
                    <y>0</y>
                    <z>0</z>
                </positie>
            </aankomst>
            <eigenaar>
                <naam>Metro</naam>
                <containernr>46150</containernr>
            </eigenaar>
            <vertrek>
                <datum>
                    <d>31</d>
                    <m>12</m>
                    <j>04</j>
                </datum>
                <tijd>
                    <van>0.00</van>
                    <tot>3.00</tot>
                </tijd>
                <soort_vervoer>binnenschip</soort_vervoer>
                <bedrijf>CapelleChartering</bedrijf>
            </vertrek>
            <afmetingen>
                <l>30'</l>
                <b>8'</b>
                <h>8'6''</h>
            </afmetingen>
            <gewicht>
                <leeg>2</leeg>
                <inhoud>31</inhoud>
            </gewicht>
            <inhoud>
                <naam>staal</naam>
                <soort>los</soort>
                <gevaar>geen</gevaar>
            </inhoud>
            <ISO>1496-1</ISO>
        </record>
        <record id="id9">
            <aankomst>
                <datum>
                    <d>9</d>
                    <m>12</m>
                    <j>04</j>
                </datum>
                <tijd>
                    <van>0.00</van>
                    <tot>0.10</tot>
                </tijd>
                <soort_vervoer>vrachtauto</soort_vervoer>
                <bedrijf>HoefnagelsTransport</bedrijf>
                <positie>
                    <x>1</x>
                    <y>0</y>
                    <z>0</z>
                </positie>
            </aankomst>
            <eigenaar>
                <naam>McDonalds</naam>
                <containernr>62037</containernr>
            </eigenaar>
            <vertrek>
                <datum>
                    <d>21</d>
                    <m>12</m>
                    <j>04</j>
                </datum>
                <tijd>
                    <van>0.00</van>
                    <tot>1.00</tot>
                </tijd>
                <soort_vervoer>trein</soort_vervoer>
                <bedrijf>NMBS</bedrijf>
            </vertrek>
            <afmetingen>
                <l>24'</l>
                <b>8'</b>
                <h>8'6''</h>
            </afmetingen>
            <gewicht>
                <leeg>2</leeg>
                <inhoud>46</inhoud>
            </gewicht>
            <inhoud>
                <naam>nitrotolueen</naam>
                <soort>gas</soort>
                <gevaar>brandbaar</gevaar>
            </inhoud>
            <ISO>1496-1</ISO>
        </record>
    </recordset>